nikescraperbykejora/__init__.py
nikescraperbykejora/datascraper.py
nikescraperbykejora/linksscraper.py
nikescraperbykejora/scrapingresult.py
nikescraperbykejora-0.4.dist-info/LICENSE
nikescraperbykejora-0.4.dist-info/METADATA
nikescraperbykejora-0.4.dist-info/WHEEL
nikescraperbykejora-0.4.dist-info/top_level.txt
nikescraperbykejora-0.4.dist-info/RECORD
