Metadata-Version: 2.1
Name: nikescraperbykejora
Version: 0.4
Summary: A simple package for scraping product information on the Nike website (nike.com/id)
Author-email: Hasan Ash <hasan40p30m@gmail.com>
Project-URL: Homepage, https://github.com/Kejoramedia/nikescraperbykejora
Classifier: Programming Language :: Python :: 3
Classifier: License :: OSI Approved :: GNU General Public License (GPL)
Classifier: Operating System :: OS Independent
Requires-Python: >=3.7
License-File: LICENSE
